{
	"info": {
		"_postman_id": "dbc9d58a-bf56-4366-a1a5-2b9073cbaee6",
		"name": "homework_7",
		"schema": "https://schema.getpostman.com/json/collection/v2.1.0/collection.json"
	},
	"item": [
		{
			"name": "users - get all",
			"request": {
				"method": "GET",
				"header": [],
				"body": {},
				"url": {
					"raw": "localhost:8080/api/users",
					"host": [
						"localhost"
					],
					"port": "8080",
					"path": [
						"api",
						"users"
					]
				}
			},
			"response": []
		},
		{
			"name": "users - add new",
			"request": {
				"method": "POST",
				"header": [
					{
						"key": "Content-Type",
						"value": "application/x-www-form-urlencoded"
					}
				],
				"body": {
					"mode": "urlencoded",
					"urlencoded": [
						{
							"key": "name",
							"value": "Bingo",
							"description": "",
							"type": "text"
						}
					]
				},
				"url": {
					"raw": "localhost:8080/api/users",
					"host": [
						"localhost"
					],
					"port": "8080",
					"path": [
						"api",
						"users"
					]
				}
			},
			"response": []
		},
		{
			"name": "users - put",
			"request": {
				"method": "PUT",
				"header": [
					{
						"key": "Content-Type",
						"value": "application/x-www-form-urlencoded"
					}
				],
				"body": {
					"mode": "urlencoded",
					"urlencoded": [
						{
							"key": "name",
							"value": "Updated Bob",
							"description": "",
							"type": "text"
						}
					]
				},
				"url": {
					"raw": "localhost:8080/api/users/1",
					"host": [
						"localhost"
					],
					"port": "8080",
					"path": [
						"api",
						"users",
						"1"
					]
				}
			},
			"response": []
		},
		{
			"name": "users - delete",
			"request": {
				"method": "DELETE",
				"header": [],
				"body": {},
				"url": {
					"raw": "localhost:8080/api/users/1",
					"host": [
						"localhost"
					],
					"port": "8080",
					"path": [
						"api",
						"users",
						"1"
					]
				}
			},
			"response": []
		},
		{
			"name": "cities - get all",
			"request": {
				"method": "GET",
				"header": [],
				"body": {},
				"url": {
					"raw": "localhost:8080/api/cities",
					"host": [
						"localhost"
					],
					"port": "8080",
					"path": [
						"api",
						"cities"
					]
				}
			},
			"response": []
		},
		{
			"name": "cities - get random",
			"request": {
				"method": "GET",
				"header": [],
				"body": {},
				"url": {
					"raw": "localhost:8080/api/cities/random",
					"host": [
						"localhost"
					],
					"port": "8080",
					"path": [
						"api",
						"cities",
						"random"
					]
				}
			},
			"response": []
		},
		{
			"name": "cities - add new",
			"request": {
				"method": "POST",
				"header": [
					{
						"key": "Content-Type",
						"value": "application/x-www-form-urlencoded"
					}
				],
				"body": {
					"mode": "urlencoded",
					"urlencoded": [
						{
							"key": "name",
							"value": "Samara",
							"description": "",
							"type": "text"
						},
						{
							"key": "country",
							"value": "Russia",
							"description": "",
							"type": "text"
						}
					]
				},
				"url": {
					"raw": "localhost:8080/api/cities",
					"host": [
						"localhost"
					],
					"port": "8080",
					"path": [
						"api",
						"cities"
					]
				}
			},
			"response": []
		},
		{
			"name": "cities - put",
			"request": {
				"method": "PUT",
				"header": [
					{
						"key": "Content-Type",
						"value": "application/x-www-form-urlencoded"
					}
				],
				"body": {
					"mode": "urlencoded",
					"urlencoded": [
						{
							"key": "country",
							"value": "Russian Federation",
							"description": "",
							"type": "text"
						},
						{
							"key": "isCapital",
							"value": "true",
							"description": "",
							"type": "text"
						},
						{
							"key": "name",
							"value": "New Moscow",
							"description": "",
							"type": "text"
						}
					]
				},
				"url": {
					"raw": "localhost:8080/api/cities/1",
					"host": [
						"localhost"
					],
					"port": "8080",
					"path": [
						"api",
						"cities",
						"1"
					]
				}
			},
			"response": []
		},
		{
			"name": "cities - delete",
			"request": {
				"method": "DELETE",
				"header": [],
				"body": {},
				"url": {
					"raw": "localhost:8080/api/cities/1",
					"host": [
						"localhost"
					],
					"port": "8080",
					"path": [
						"api",
						"cities",
						"1"
					]
				}
			},
			"response": []
		},
		{
			"name": "products - get all",
			"request": {
				"method": "GET",
				"header": [],
				"body": {},
				"url": {
					"raw": "localhost:8080/api/products",
					"host": [
						"localhost"
					],
					"port": "8080",
					"path": [
						"api",
						"products"
					]
				}
			},
			"response": []
		},
		{
			"name": "products - add new",
			"request": {
				"method": "POST",
				"header": [
					{
						"key": "Content-Type",
						"value": "application/x-www-form-urlencoded"
					}
				],
				"body": {
					"mode": "urlencoded",
					"urlencoded": [
						{
							"key": "name",
							"value": "SomethingNew",
							"description": "",
							"type": "text"
						},
						{
							"key": "desc",
							"value": "This is something new!",
							"description": "",
							"type": "text"
						}
					]
				},
				"url": {
					"raw": "localhost:8080/api/products",
					"host": [
						"localhost"
					],
					"port": "8080",
					"path": [
						"api",
						"products"
					]
				}
			},
			"response": []
		},
		{
			"name": "products - put",
			"request": {
				"method": "PUT",
				"header": [
					{
						"key": "Content-Type",
						"value": "application/x-www-form-urlencoded"
					}
				],
				"body": {
					"mode": "urlencoded",
					"urlencoded": [
						{
							"key": "desc",
							"value": "Updated! Not bright and not boldy at all!",
							"description": "",
							"type": "text"
						}
					]
				},
				"url": {
					"raw": "localhost:8080/api/products/1",
					"host": [
						"localhost"
					],
					"port": "8080",
					"path": [
						"api",
						"products",
						"1"
					]
				}
			},
			"response": []
		},
		{
			"name": "products - delete",
			"request": {
				"method": "DELETE",
				"header": [],
				"body": {},
				"url": {
					"raw": "localhost:8080/api/products/1",
					"host": [
						"localhost"
					],
					"port": "8080",
					"path": [
						"api",
						"products",
						"1"
					]
				}
			},
			"response": []
		}
	]
}